httpfrost/__init__.py
httpfrost/server.py
httpfrost-1.0.0.dist-info/licenses/LICENSE
pyshare/__init__.py
pyshare/server.py
httpfrost-1.0.0.dist-info/METADATA
httpfrost-1.0.0.dist-info/WHEEL
httpfrost-1.0.0.dist-info/entry_points.txt
httpfrost-1.0.0.dist-info/top_level.txt
httpfrost-1.0.0.dist-info/RECORD
