Metadata-Version: 2.4
Name: httpfrost
Version: 1.0.0
Summary: Secure LAN file sharing HTTP server with upload and selective ZIP download
Author: James Majura
Author-email: captainmajura@gmail.com
Classifier: Programming Language :: Python :: 3
Classifier: Operating System :: OS Independent
Requires-Python: >=3.7
License-File: LICENSE
Dynamic: author
Dynamic: author-email
Dynamic: classifier
Dynamic: license-file
Dynamic: requires-python
Dynamic: summary
